<Document doc_name="Dd007#2.txt">
<token t_id="1" sentence="0" number="0">COMMENT:</token>
<token t_id="2" sentence="0" number="1">As</token>
<token t_id="3" sentence="0" number="2">a</token>
<token t_id="4" sentence="0" number="3">depression-prone</token>
<token t_id="5" sentence="0" number="4">person,</token>
<token t_id="6" sentence="0" number="5">I</token>
<token t_id="7" sentence="0" number="6">agree</token>
<token t_id="8" sentence="0" number="7">with</token>
<token t_id="9" sentence="0" number="8">that</token>
<token t_id="10" sentence="0" number="9">portion</token>
<token t_id="11" sentence="0" number="10">of</token>
<token t_id="12" sentence="0" number="11">the</token>
<token t_id="13" sentence="0" number="12">column</token>
<token t_id="14" sentence="0" number="13">most</token>
<token t_id="15" sentence="0" number="14">strongly.</token>
<token t_id="16" sentence="0" number="15">Every</token>
<token t_id="17" sentence="0" number="16">non-specialist</token>
<token t_id="18" sentence="0" number="17">that</token>
<token t_id="19" sentence="0" number="18">I</token>
<token t_id="20" sentence="0" number="19">met</token>
<token t_id="21" sentence="0" number="20">as</token>
<token t_id="22" sentence="0" number="21">an</token>
<token t_id="23" sentence="0" number="22">adolescent</token>
<token t_id="24" sentence="0" number="23">was</token>
<token t_id="25" sentence="0" number="24">unfamiliar</token>
<token t_id="26" sentence="0" number="25">with</token>
<token t_id="27" sentence="0" number="26">(or</token>
<token t_id="28" sentence="0" number="27">at</token>
<token t_id="29" sentence="0" number="28">least</token>
<token t_id="30" sentence="0" number="29">unwilling</token>
<token t_id="31" sentence="0" number="30">to</token>
<token t_id="32" sentence="0" number="31">talk</token>
<token t_id="33" sentence="0" number="32">about)</token>
<token t_id="34" sentence="0" number="33">depression</token>
<token t_id="35" sentence="0" number="34">and</token>
<token t_id="36" sentence="0" number="35">social</token>
<token t_id="37" sentence="0" number="36">anxiety.</token>
<token t_id="38" sentence="0" number="37">Granted,</token>
<token t_id="39" sentence="0" number="38">this</token>
<token t_id="40" sentence="0" number="39">was</token>
<token t_id="41" sentence="0" number="40">before</token>
<token t_id="42" sentence="0" number="41">the</token>
<token t_id="43" sentence="0" number="42">Prozac</token>
<token t_id="44" sentence="0" number="43">and</token>
<token t_id="45" sentence="0" number="44">computer</token>
<token t_id="46" sentence="0" number="45">revolutions,</token>
<token t_id="47" sentence="0" number="46">but</token>
<token t_id="48" sentence="0" number="47">I've</token>
<token t_id="49" sentence="0" number="48">spent</token>
<token t_id="50" sentence="0" number="49">much</token>
<token t_id="51" sentence="0" number="50">of</token>
<token t_id="52" sentence="0" number="51">my</token>
<token t_id="53" sentence="0" number="52">life</token>
<token t_id="54" sentence="0" number="53">engaged</token>
<token t_id="55" sentence="0" number="54">in</token>
<token t_id="56" sentence="0" number="55">problematic</token>
<token t_id="57" sentence="0" number="56">use</token>
<token t_id="58" sentence="0" number="57">of</token>
<token t_id="59" sentence="0" number="58">computers.</token>
<token t_id="60" sentence="0" number="59">At</token>
<token t_id="61" sentence="0" number="60">least</token>
<token t_id="62" sentence="0" number="61">we</token>
<token t_id="63" sentence="0" number="62">need</token>
<token t_id="64" sentence="0" number="63">to</token>
<token t_id="65" sentence="0" number="64">be</token>
<token t_id="66" sentence="0" number="65">aware</token>
<token t_id="67" sentence="0" number="66">of</token>
<token t_id="68" sentence="0" number="67">the</token>
<token t_id="69" sentence="0" number="68">potential</token>
<token t_id="70" sentence="0" number="69">for</token>
<token t_id="71" sentence="0" number="70">serious</token>
<token t_id="72" sentence="0" number="71">mental</token>
<token t_id="73" sentence="0" number="72">and</token>
<token t_id="74" sentence="0" number="73">brain</token>
<token t_id="75" sentence="0" number="74">damage</token>
<token t_id="76" sentence="0" number="75">to</token>
<token t_id="77" sentence="0" number="76">occur.</token>
<token t_id="78" sentence="0" number="77">Anyone</token>
<token t_id="79" sentence="0" number="78">who</token>
<token t_id="80" sentence="0" number="79">wants</token>
<token t_id="81" sentence="0" number="80">a</token>
<token t_id="82" sentence="0" number="81">good</token>
<token t_id="83" sentence="0" number="82">example</token>
<token t_id="84" sentence="0" number="83">of</token>
<token t_id="85" sentence="0" number="84">kids</token>
<token t_id="86" sentence="0" number="85">who</token>
<token t_id="87" sentence="0" number="86">have</token>
<token t_id="88" sentence="0" number="87">had</token>
<token t_id="89" sentence="0" number="88">their</token>
<token t_id="90" sentence="0" number="89">lives</token>
<token t_id="91" sentence="0" number="90">virtually</token>
<token t_id="92" sentence="0" number="91">destroyed</token>
<token t_id="93" sentence="0" number="92">by</token>
<token t_id="94" sentence="0" number="93">computer</token>
<token t_id="95" sentence="0" number="94">addiction</token>
<token t_id="96" sentence="0" number="95">should</token>
<token t_id="97" sentence="0" number="96">watch</token>
<token t_id="98" sentence="0" number="97">the</token>
<token t_id="99" sentence="0" number="98">Frontline</token>
<token t_id="100" sentence="0" number="99">program</token>
<token t_id="101" sentence="0" number="100">"Web</token>
<token t_id="102" sentence="0" number="101">Junkies."</token>
<token t_id="103" sentence="0" number="102">I</token>
<token t_id="104" sentence="0" number="103">was</token>
<token t_id="105" sentence="0" number="104">aghast</token>
<token t_id="106" sentence="0" number="105">as</token>
<token t_id="107" sentence="0" number="106">how</token>
<token t_id="108" sentence="0" number="107">deeply</token>
<token t_id="109" sentence="0" number="108">sunk</token>
<token t_id="110" sentence="0" number="109">into</token>
<token t_id="111" sentence="0" number="110">compulsive</token>
<token t_id="112" sentence="0" number="111">behavior</token>
<token t_id="113" sentence="0" number="112">some</token>
<token t_id="114" sentence="0" number="113">kids</token>
<token t_id="115" sentence="0" number="114">can</token>
<token t_id="116" sentence="0" number="115">find</token>
<token t_id="117" sentence="0" number="116">themselves.</token>
<token t_id="118" sentence="0" number="117">Since</token>
<token t_id="119" sentence="0" number="118">total</token>
<token t_id="120" sentence="0" number="119">abstinence</token>
<token t_id="121" sentence="0" number="120">from</token>
<token t_id="122" sentence="0" number="121">use</token>
<token t_id="123" sentence="0" number="122">of</token>
<token t_id="124" sentence="0" number="123">computers</token>
<token t_id="125" sentence="0" number="124">is</token>
<token t_id="126" sentence="0" number="125">virtually</token>
<token t_id="127" sentence="0" number="126">not</token>
<token t_id="128" sentence="0" number="127">an</token>
<token t_id="129" sentence="0" number="128">option</token>
<token t_id="130" sentence="0" number="129">these</token>
<token t_id="131" sentence="0" number="130">days,</token>
<token t_id="132" sentence="0" number="131">recovery</token>
<token t_id="133" sentence="0" number="132">from</token>
<token t_id="134" sentence="0" number="133">addiction</token>
<token t_id="135" sentence="0" number="134">is</token>
<token t_id="136" sentence="0" number="135">terrifyingly</token>
<token t_id="137" sentence="0" number="136">difficult.</token>
<token t_id="138" sentence="1" number="137">Cyberbullying</token>
<token t_id="139" sentence="1" number="138">Is</token>
<token t_id="140" sentence="1" number="139">a</token>
<token t_id="141" sentence="1" number="140">Bigger</token>
<token t_id="142" sentence="1" number="141">Problem</token>
<token t_id="143" sentence="1" number="142">Than</token>
<token t_id="144" sentence="1" number="143">Screen</token>
<token t_id="145" sentence="1" number="144">Time</token>
<token t_id="146" sentence="1" number="145">Addiction</token>
<token t_id="147" sentence="1" number="146">.</token>
<token t_id="148" sentence="2" number="147">The</token>
<token t_id="149" sentence="2" number="148">harms</token>
<token t_id="150" sentence="2" number="149">that</token>
<token t_id="151" sentence="2" number="150">can</token>
<token t_id="152" sentence="2" number="151">come</token>
<token t_id="153" sentence="2" number="152">to</token>
<token t_id="154" sentence="2" number="153">children</token>
<token t_id="155" sentence="2" number="154">who</token>
<token t_id="156" sentence="2" number="155">use</token>
<token t_id="157" sentence="2" number="156">technology</token>
<token t_id="158" sentence="2" number="157">excessively</token>
<token t_id="159" sentence="2" number="158">-</token>
<token t_id="160" sentence="2" number="159">including</token>
<token t_id="161" sentence="2" number="160">depression</token>
<token t_id="162" sentence="2" number="161">,</token>
<token t_id="163" sentence="2" number="162">behavioral</token>
<token t_id="164" sentence="2" number="163">problems</token>
<token t_id="165" sentence="2" number="164">and</token>
<token t_id="166" sentence="2" number="165">poor</token>
<token t_id="167" sentence="2" number="166">academic</token>
<token t_id="168" sentence="2" number="167">performance</token>
<token t_id="169" sentence="2" number="168">-</token>
<token t_id="170" sentence="2" number="169">are</token>
<token t_id="171" sentence="2" number="170">not</token>
<token t_id="172" sentence="2" number="171">just</token>
<token t_id="173" sentence="2" number="172">caused</token>
<token t_id="174" sentence="2" number="173">by</token>
<token t_id="175" sentence="2" number="174">too</token>
<token t_id="176" sentence="2" number="175">much</token>
<token t_id="177" sentence="2" number="176">screen</token>
<token t_id="178" sentence="2" number="177">time</token>
<token t_id="179" sentence="2" number="178">.</token>
<token t_id="180" sentence="3" number="179">It</token>
<token t_id="181" sentence="3" number="180">is</token>
<token t_id="182" sentence="3" number="181">the</token>
<token t_id="183" sentence="3" number="182">nature</token>
<token t_id="184" sentence="3" number="183">of</token>
<token t_id="185" sentence="3" number="184">the</token>
<token t_id="186" sentence="3" number="185">interactions</token>
<token t_id="187" sentence="3" number="186">that</token>
<token t_id="188" sentence="3" number="187">take</token>
<token t_id="189" sentence="3" number="188">place</token>
<token t_id="190" sentence="3" number="189">through</token>
<token t_id="191" sentence="3" number="190">the</token>
<token t_id="192" sentence="3" number="191">screen</token>
<token t_id="193" sentence="3" number="192">that</token>
<token t_id="194" sentence="3" number="193">count</token>
<token t_id="195" sentence="3" number="194">.</token>
<token t_id="196" sentence="4" number="195">Simply</token>
<token t_id="197" sentence="4" number="196">limiting</token>
<token t_id="198" sentence="4" number="197">screen</token>
<token t_id="199" sentence="4" number="198">time</token>
<token t_id="200" sentence="4" number="199">ignores</token>
<token t_id="201" sentence="4" number="200">the</token>
<token t_id="202" sentence="4" number="201">many</token>
<token t_id="203" sentence="4" number="202">benefits</token>
<token t_id="204" sentence="4" number="203">of</token>
<token t_id="205" sentence="4" number="204">technology</token>
<token t_id="206" sentence="4" number="205">for</token>
<token t_id="207" sentence="4" number="206">teenagers</token>
<token t_id="208" sentence="4" number="207">.</token>
<token t_id="209" sentence="5" number="208">But</token>
<token t_id="210" sentence="5" number="209">cybervictimization</token>
<token t_id="211" sentence="5" number="210">is</token>
<token t_id="212" sentence="5" number="211">a</token>
<token t_id="213" sentence="5" number="212">problem</token>
<token t_id="214" sentence="5" number="213">that</token>
<token t_id="215" sentence="5" number="214">'s</token>
<token t_id="216" sentence="5" number="215">become</token>
<token t_id="217" sentence="5" number="216">pervasive</token>
<token t_id="218" sentence="5" number="217">.</token>
<token t_id="219" sentence="6" number="218">The</token>
<token t_id="220" sentence="6" number="219">bullies</token>
<token t_id="221" sentence="6" number="220">have</token>
<token t_id="222" sentence="6" number="221">moved</token>
<token t_id="223" sentence="6" number="222">from</token>
<token t_id="224" sentence="6" number="223">the</token>
<token t_id="225" sentence="6" number="224">playground</token>
<token t_id="226" sentence="6" number="225">to</token>
<token t_id="227" sentence="6" number="226">the</token>
<token t_id="228" sentence="6" number="227">mobile</token>
<token t_id="229" sentence="6" number="228">screen</token>
<token t_id="230" sentence="6" number="229">,</token>
<token t_id="231" sentence="6" number="230">and</token>
<token t_id="232" sentence="6" number="231">there</token>
<token t_id="233" sentence="6" number="232">is</token>
<token t_id="234" sentence="6" number="233">no</token>
<token t_id="235" sentence="6" number="234">escaping</token>
<token t_id="236" sentence="6" number="235">harassment</token>
<token t_id="237" sentence="6" number="236">that</token>
<token t_id="238" sentence="6" number="237">essentially</token>
<token t_id="239" sentence="6" number="238">lives</token>
<token t_id="240" sentence="6" number="239">in</token>
<token t_id="241" sentence="6" number="240">your</token>
<token t_id="242" sentence="6" number="241">pocket</token>
<token t_id="243" sentence="6" number="242">.</token>
<token t_id="244" sentence="7" number="243">Bullying</token>
<token t_id="245" sentence="7" number="244">and</token>
<token t_id="246" sentence="7" number="245">online</token>
<token t_id="247" sentence="7" number="246">harassment</token>
<token t_id="248" sentence="7" number="247">increases</token>
<token t_id="249" sentence="7" number="248">anxiety</token>
<token t_id="250" sentence="7" number="249">and</token>
<token t_id="251" sentence="7" number="250">depression</token>
<token t_id="252" sentence="7" number="251">,</token>
<token t_id="253" sentence="7" number="252">and</token>
<token t_id="254" sentence="7" number="253">it</token>
<token t_id="255" sentence="7" number="254">often</token>
<token t_id="256" sentence="7" number="255">compounds</token>
<token t_id="257" sentence="7" number="256">mental</token>
<token t_id="258" sentence="7" number="257">health</token>
<token t_id="259" sentence="7" number="258">problems</token>
<token t_id="260" sentence="7" number="259">over</token>
<token t_id="261" sentence="7" number="260">multiple</token>
<token t_id="262" sentence="7" number="261">years</token>
<token t_id="263" sentence="7" number="262">.</token>
<token t_id="264" sentence="8" number="263">In</token>
<token t_id="265" sentence="8" number="264">particular</token>
<token t_id="266" sentence="8" number="265">,</token>
<token t_id="267" sentence="8" number="266">race-related</token>
<token t_id="268" sentence="8" number="267">online</token>
<token t_id="269" sentence="8" number="268">victimization</token>
<token t_id="270" sentence="8" number="269">-</token>
<token t_id="271" sentence="8" number="270">including</token>
<token t_id="272" sentence="8" number="271">the</token>
<token t_id="273" sentence="8" number="272">circulation</token>
<token t_id="274" sentence="8" number="273">of</token>
<token t_id="275" sentence="8" number="274">racist</token>
<token t_id="276" sentence="8" number="275">imagery</token>
<token t_id="277" sentence="8" number="276">-</token>
<token t_id="278" sentence="8" number="277">is</token>
<token t_id="279" sentence="8" number="278">on</token>
<token t_id="280" sentence="8" number="279">the</token>
<token t_id="281" sentence="8" number="280">rise</token>
<token t_id="282" sentence="8" number="281">,</token>
<token t_id="283" sentence="8" number="282">with</token>
<token t_id="284" sentence="8" number="283">50</token>
<token t_id="285" sentence="8" number="284">percent</token>
<token t_id="286" sentence="8" number="285">of</token>
<token t_id="287" sentence="8" number="286">adolescents</token>
<token t_id="288" sentence="8" number="287">of</token>
<token t_id="289" sentence="8" number="288">color</token>
<token t_id="290" sentence="8" number="289">reporting</token>
<token t_id="291" sentence="8" number="290">these</token>
<token t_id="292" sentence="8" number="291">incidents</token>
<token t_id="293" sentence="8" number="292">in</token>
<token t_id="294" sentence="8" number="293">2013</token>
<token t_id="295" sentence="8" number="294">,</token>
<token t_id="296" sentence="8" number="295">up</token>
<token t_id="297" sentence="8" number="296">from</token>
<token t_id="298" sentence="8" number="297">32</token>
<token t_id="299" sentence="8" number="298">percent</token>
<token t_id="300" sentence="8" number="299">in</token>
<token t_id="301" sentence="8" number="300">2011</token>
<token t_id="302" sentence="8" number="301">,</token>
<token t_id="303" sentence="8" number="302">according</token>
<token t_id="304" sentence="8" number="303">to</token>
<token t_id="305" sentence="8" number="304">my</token>
<token t_id="306" sentence="8" number="305">own</token>
<token t_id="307" sentence="8" number="306">research</token>
<token t_id="308" sentence="8" number="307">.</token>
<token t_id="309" sentence="9" number="308">These</token>
<token t_id="310" sentence="9" number="309">incidents</token>
<token t_id="311" sentence="9" number="310">are</token>
<token t_id="312" sentence="9" number="311">associated</token>
<token t_id="313" sentence="9" number="312">with</token>
<token t_id="314" sentence="9" number="313">poor</token>
<token t_id="315" sentence="9" number="314">mental</token>
<token t_id="316" sentence="9" number="315">health</token>
<token t_id="317" sentence="9" number="316">and</token>
<token t_id="318" sentence="9" number="317">well-being</token>
<token t_id="319" sentence="9" number="318">,</token>
<token t_id="320" sentence="9" number="319">as</token>
<token t_id="321" sentence="9" number="320">well</token>
<token t_id="322" sentence="9" number="321">as</token>
<token t_id="323" sentence="9" number="322">decreased</token>
<token t_id="324" sentence="9" number="323">academic</token>
<token t_id="325" sentence="9" number="324">motivation</token>
<token t_id="326" sentence="9" number="325">and</token>
<token t_id="327" sentence="9" number="326">behavioral</token>
<token t_id="328" sentence="9" number="327">problems</token>
<token t_id="329" sentence="9" number="328">.</token>
<token t_id="330" sentence="10" number="329">But</token>
<token t_id="331" sentence="10" number="330">scholars</token>
<token t_id="332" sentence="10" number="331">are</token>
<token t_id="333" sentence="10" number="332">beginning</token>
<token t_id="334" sentence="10" number="333">to</token>
<token t_id="335" sentence="10" number="334">make</token>
<token t_id="336" sentence="10" number="335">distinctions</token>
<token t_id="337" sentence="10" number="336">between</token>
<token t_id="338" sentence="10" number="337">screen</token>
<token t_id="339" sentence="10" number="338">time</token>
<token t_id="340" sentence="10" number="339">that</token>
<token t_id="341" sentence="10" number="340">interferes</token>
<token t_id="342" sentence="10" number="341">with</token>
<token t_id="343" sentence="10" number="342">functioning</token>
<token t_id="344" sentence="10" number="343">,</token>
<token t_id="345" sentence="10" number="344">and</token>
<token t_id="346" sentence="10" number="345">that</token>
<token t_id="347" sentence="10" number="346">which</token>
<token t_id="348" sentence="10" number="347">leads</token>
<token t_id="349" sentence="10" number="348">to</token>
<token t_id="350" sentence="10" number="349">more</token>
<token t_id="351" sentence="10" number="350">positive</token>
<token t_id="352" sentence="10" number="351">engagement</token>
<token t_id="353" sentence="10" number="352">.</token>
<token t_id="354" sentence="11" number="353">With</token>
<token t_id="355" sentence="11" number="354">respect</token>
<token t_id="356" sentence="11" number="355">to</token>
<token t_id="357" sentence="11" number="356">problematic</token>
<token t_id="358" sentence="11" number="357">video</token>
<token t_id="359" sentence="11" number="358">game</token>
<token t_id="360" sentence="11" number="359">playing</token>
<token t_id="361" sentence="11" number="360">,</token>
<token t_id="362" sentence="11" number="361">for</token>
<token t_id="363" sentence="11" number="362">example</token>
<token t_id="364" sentence="11" number="363">,</token>
<token t_id="365" sentence="11" number="364">those</token>
<token t_id="366" sentence="11" number="365">who</token>
<token t_id="367" sentence="11" number="366">might</token>
<token t_id="368" sentence="11" number="367">be</token>
<token t_id="369" sentence="11" number="368">considered</token>
<token t_id="370" sentence="11" number="369">``</token>
<token t_id="371" sentence="11" number="370">addicted</token>
<token t_id="372" sentence="11" number="371">''</token>
<token t_id="373" sentence="11" number="372">include</token>
<token t_id="374" sentence="11" number="373">only</token>
<token t_id="375" sentence="11" number="374">about</token>
<token t_id="376" sentence="11" number="375">3</token>
<token t_id="377" sentence="11" number="376">to</token>
<token t_id="378" sentence="11" number="377">5</token>
<token t_id="379" sentence="11" number="378">percent</token>
<token t_id="380" sentence="11" number="379">of</token>
<token t_id="381" sentence="11" number="380">adolescents</token>
<token t_id="382" sentence="11" number="381">.</token>
<token t_id="383" sentence="12" number="382">By</token>
<token t_id="384" sentence="12" number="383">contrast</token>
<token t_id="385" sentence="12" number="384">,</token>
<token t_id="386" sentence="12" number="385">video</token>
<token t_id="387" sentence="12" number="386">game</token>
<token t_id="388" sentence="12" number="387">playing</token>
<token t_id="389" sentence="12" number="388">,</token>
<token t_id="390" sentence="12" number="389">regardless</token>
<token t_id="391" sentence="12" number="390">of</token>
<token t_id="392" sentence="12" number="391">type</token>
<token t_id="393" sentence="12" number="392">,</token>
<token t_id="394" sentence="12" number="393">has</token>
<token t_id="395" sentence="12" number="394">also</token>
<token t_id="396" sentence="12" number="395">been</token>
<token t_id="397" sentence="12" number="396">linked</token>
<token t_id="398" sentence="12" number="397">to</token>
<token t_id="399" sentence="12" number="398">creativity</token>
<token t_id="400" sentence="12" number="399">in</token>
<token t_id="401" sentence="12" number="400">middle</token>
<token t_id="402" sentence="12" number="401">school</token>
<token t_id="403" sentence="12" number="402">students</token>
<token t_id="404" sentence="12" number="403">.</token>
<token t_id="405" sentence="13" number="404">We</token>
<token t_id="406" sentence="13" number="405">don'</token>
<token t_id="407" sentence="13" number="406">t</token>
<token t_id="408" sentence="13" number="407">yet</token>
<token t_id="409" sentence="13" number="408">know</token>
<token t_id="410" sentence="13" number="409">how</token>
<token t_id="411" sentence="13" number="410">much</token>
<token t_id="412" sentence="13" number="411">screen</token>
<token t_id="413" sentence="13" number="412">time</token>
<token t_id="414" sentence="13" number="413">for</token>
<token t_id="415" sentence="13" number="414">positive</token>
<token t_id="416" sentence="13" number="415">uses</token>
<token t_id="417" sentence="13" number="416">,</token>
<token t_id="418" sentence="13" number="417">such</token>
<token t_id="419" sentence="13" number="418">as</token>
<token t_id="420" sentence="13" number="419">content</token>
<token t_id="421" sentence="13" number="420">creation</token>
<token t_id="422" sentence="13" number="421">,</token>
<token t_id="423" sentence="13" number="422">is</token>
<token t_id="424" sentence="13" number="423">too</token>
<token t_id="425" sentence="13" number="424">much</token>
<token t_id="426" sentence="13" number="425">.</token>
<token t_id="427" sentence="14" number="426">But</token>
<token t_id="428" sentence="14" number="427">certain</token>
<token t_id="429" sentence="14" number="428">examples</token>
<token t_id="430" sentence="14" number="429">of</token>
<token t_id="431" sentence="14" number="430">good</token>
<token t_id="432" sentence="14" number="431">works</token>
<token t_id="433" sentence="14" number="432">-</token>
<token t_id="434" sentence="14" number="433">like</token>
<token t_id="435" sentence="14" number="434">that</token>
<token t_id="436" sentence="14" number="435">of</token>
<token t_id="437" sentence="14" number="436">six</token>
<token t_id="438" sentence="14" number="437">middle</token>
<token t_id="439" sentence="14" number="438">school</token>
<token t_id="440" sentence="14" number="439">girls</token>
<token t_id="441" sentence="14" number="440">who</token>
<token t_id="442" sentence="14" number="441">spent</token>
<token t_id="443" sentence="14" number="442">hours</token>
<token t_id="444" sentence="14" number="443">buried</token>
<token t_id="445" sentence="14" number="444">in</token>
<token t_id="446" sentence="14" number="445">code</token>
<token t_id="447" sentence="14" number="446">,</token>
<token t_id="448" sentence="14" number="447">and</token>
<token t_id="449" sentence="14" number="448">created</token>
<token t_id="450" sentence="14" number="449">an</token>
<token t_id="451" sentence="14" number="450">app</token>
<token t_id="452" sentence="14" number="451">to</token>
<token t_id="453" sentence="14" number="452">help</token>
<token t_id="454" sentence="14" number="453">their</token>
<token t_id="455" sentence="14" number="454">blind</token>
<token t_id="456" sentence="14" number="455">classmate</token>
<token t_id="457" sentence="14" number="456">get</token>
<token t_id="458" sentence="14" number="457">around</token>
<token t_id="459" sentence="14" number="458">campus</token>
<token t_id="460" sentence="14" number="459">-</token>
<token t_id="461" sentence="14" number="460">remind</token>
<token t_id="462" sentence="14" number="461">us</token>
<token t_id="463" sentence="14" number="462">of</token>
<token t_id="464" sentence="14" number="463">the</token>
<token t_id="465" sentence="14" number="464">good</token>
<token t_id="466" sentence="14" number="465">that</token>
<token t_id="467" sentence="14" number="466">children</token>
<token t_id="468" sentence="14" number="467">and</token>
<token t_id="469" sentence="14" number="468">teenagers</token>
<token t_id="470" sentence="14" number="469">can</token>
<token t_id="471" sentence="14" number="470">do</token>
<token t_id="472" sentence="14" number="471">with</token>
<token t_id="473" sentence="14" number="472">their</token>
<token t_id="474" sentence="14" number="473">screen</token>
<token t_id="475" sentence="14" number="474">time</token>
<token t_id="476" sentence="14" number="475">.</token>
<token t_id="477" sentence="15" number="476">Of</token>
<token t_id="478" sentence="15" number="477">course</token>
<token t_id="479" sentence="15" number="478">,</token>
<token t_id="480" sentence="15" number="479">we</token>
<token t_id="481" sentence="15" number="480">wouldn'</token>
<token t_id="482" sentence="15" number="481">t</token>
<token t_id="483" sentence="15" number="482">want</token>
<token t_id="484" sentence="15" number="483">them</token>
<token t_id="485" sentence="15" number="484">to</token>
<token t_id="486" sentence="15" number="485">forsake</token>
<token t_id="487" sentence="15" number="486">their</token>
<token t_id="488" sentence="15" number="487">schoolwork</token>
<token t_id="489" sentence="15" number="488">or</token>
<token t_id="490" sentence="15" number="489">personal</token>
<token t_id="491" sentence="15" number="490">relationships</token>
<token t_id="492" sentence="15" number="491">,</token>
<token t_id="493" sentence="15" number="492">but</token>
<token t_id="494" sentence="15" number="493">would</token>
<token t_id="495" sentence="15" number="494">we</token>
<token t_id="496" sentence="15" number="495">call</token>
<token t_id="497" sentence="15" number="496">that</token>
<token t_id="498" sentence="15" number="497">kind</token>
<token t_id="499" sentence="15" number="498">of</token>
<token t_id="500" sentence="15" number="499">drive</token>
<token t_id="501" sentence="15" number="500">and</token>
<token t_id="502" sentence="15" number="501">focus</token>
<token t_id="503" sentence="15" number="502">an</token>
<token t_id="504" sentence="15" number="503">``</token>
<token t_id="505" sentence="15" number="504">addiction</token>
<token t_id="506" sentence="15" number="505">''</token>
<token t_id="507" sentence="15" number="506">?</token>


<Markables>
<COMMENTED_UPON m_id="1" comment=""  >
<token_anchor t_id="244"/>
<token_anchor t_id="245"/>
<token_anchor t_id="246"/>
<token_anchor t_id="247"/>
<token_anchor t_id="248"/>
<token_anchor t_id="249"/>
<token_anchor t_id="250"/>
<token_anchor t_id="251"/>
<token_anchor t_id="252"/>
<token_anchor t_id="253"/>
<token_anchor t_id="254"/>
<token_anchor t_id="255"/>
<token_anchor t_id="256"/>
<token_anchor t_id="257"/>
<token_anchor t_id="258"/>
<token_anchor t_id="259"/>
<token_anchor t_id="260"/>
<token_anchor t_id="261"/>
<token_anchor t_id="262"/>
<token_anchor t_id="263"/>
</COMMENTED_UPON>
<COMMENTED_UPON m_id="2" comment=""  >
<token_anchor t_id="309"/>
<token_anchor t_id="310"/>
<token_anchor t_id="311"/>
<token_anchor t_id="312"/>
<token_anchor t_id="313"/>
<token_anchor t_id="314"/>
<token_anchor t_id="315"/>
<token_anchor t_id="316"/>
<token_anchor t_id="317"/>
<token_anchor t_id="318"/>
<token_anchor t_id="319"/>
<token_anchor t_id="320"/>
<token_anchor t_id="321"/>
<token_anchor t_id="322"/>
<token_anchor t_id="323"/>
<token_anchor t_id="324"/>
<token_anchor t_id="325"/>
<token_anchor t_id="326"/>
<token_anchor t_id="327"/>
<token_anchor t_id="328"/>
<token_anchor t_id="329"/>
</COMMENTED_UPON>
<COMMENTED_UPON m_id="3" comment=""  >
<token_anchor t_id="209"/>
<token_anchor t_id="210"/>
<token_anchor t_id="211"/>
<token_anchor t_id="212"/>
<token_anchor t_id="213"/>
<token_anchor t_id="214"/>
<token_anchor t_id="215"/>
<token_anchor t_id="216"/>
<token_anchor t_id="217"/>
<token_anchor t_id="218"/>
</COMMENTED_UPON>
<COMMENTED_UPON m_id="4" comment=""  >
<token_anchor t_id="148"/>
<token_anchor t_id="149"/>
<token_anchor t_id="150"/>
<token_anchor t_id="151"/>
<token_anchor t_id="152"/>
<token_anchor t_id="153"/>
<token_anchor t_id="154"/>
<token_anchor t_id="155"/>
<token_anchor t_id="156"/>
<token_anchor t_id="157"/>
<token_anchor t_id="158"/>
<token_anchor t_id="159"/>
<token_anchor t_id="160"/>
<token_anchor t_id="161"/>
<token_anchor t_id="162"/>
<token_anchor t_id="163"/>
<token_anchor t_id="164"/>
<token_anchor t_id="165"/>
<token_anchor t_id="166"/>
<token_anchor t_id="167"/>
<token_anchor t_id="168"/>
<token_anchor t_id="169"/>
<token_anchor t_id="170"/>
<token_anchor t_id="171"/>
<token_anchor t_id="172"/>
<token_anchor t_id="173"/>
<token_anchor t_id="174"/>
<token_anchor t_id="175"/>
<token_anchor t_id="176"/>
<token_anchor t_id="177"/>
<token_anchor t_id="178"/>
<token_anchor t_id="179"/>
</COMMENTED_UPON>
<COMMENTED_UPON m_id="5" comment=""  >
<token_anchor t_id="354"/>
<token_anchor t_id="355"/>
<token_anchor t_id="356"/>
<token_anchor t_id="357"/>
<token_anchor t_id="358"/>
<token_anchor t_id="359"/>
<token_anchor t_id="360"/>
<token_anchor t_id="361"/>
<token_anchor t_id="362"/>
<token_anchor t_id="363"/>
<token_anchor t_id="364"/>
<token_anchor t_id="365"/>
<token_anchor t_id="366"/>
<token_anchor t_id="367"/>
<token_anchor t_id="368"/>
<token_anchor t_id="369"/>
<token_anchor t_id="370"/>
<token_anchor t_id="371"/>
<token_anchor t_id="372"/>
<token_anchor t_id="373"/>
<token_anchor t_id="374"/>
<token_anchor t_id="375"/>
<token_anchor t_id="376"/>
<token_anchor t_id="377"/>
<token_anchor t_id="378"/>
<token_anchor t_id="379"/>
<token_anchor t_id="380"/>
<token_anchor t_id="381"/>
</COMMENTED_UPON>


</Markables>

<Relations>
</Relations>
</Document>
